cao_cli/__init__.py
cao_cli/cache.json
cao_cli/git_helper.py
cao_cli/main.py
cao_cli/temp.log
cao_cli-1.0.8.dist-info/entry_points.txt
cao_cli-1.0.8.dist-info/WHEEL
cao_cli-1.0.8.dist-info/METADATA
cao_cli-1.0.8.dist-info/RECORD
