Metadata-Version: 2.1
Name: cao-cli
Version: 1.0.8
Summary: 
Author: chenwei.hander
Author-email: chenwei.hander@bytedance.com
Requires-Python: >=3.6,<4.0
Classifier: Programming Language :: Python :: 3
Classifier: Programming Language :: Python :: 3.10
Classifier: Programming Language :: Python :: 3.6
Classifier: Programming Language :: Python :: 3.7
Classifier: Programming Language :: Python :: 3.8
Classifier: Programming Language :: Python :: 3.9
Requires-Dist: pyperclip (>=1.8.2,<2.0.0)
Requires-Dist: tabulate (>=0.8.9,<0.9.0)
Requires-Dist: typer (>=0.4.1,<0.5.0)
Requires-Dist: wcwidth (>=0.2.5,<0.3.0)
